cargo/__init__.py
cargo/cargo.py
cargo/helper.py
cargo/metrics/__init__.py
cargo/metrics/metric_utils.py
cargo/metrics/metrics.py
cargo/utils/__init__.py
cargo/utils/logging.py
cargo/utils/progress_bar_factory.py
minerva_cargo-1.1.0.dist-info/LICENSE
minerva_cargo-1.1.0.dist-info/METADATA
minerva_cargo-1.1.0.dist-info/WHEEL
minerva_cargo-1.1.0.dist-info/top_level.txt
minerva_cargo-1.1.0.dist-info/RECORD
