Metadata-Version: 2.1
Name: minerva-cargo
Version: 1.1.0
Summary: A data-centric transformation of monoliths into microservices
Home-page: https://github.com/ibm/codenet-minerva-cargo
Author: Rahul Krishna
Classifier: Development Status :: 2 - Pre-Alpha
Classifier: Environment :: Console
Classifier: Intended Audience :: Developers
Classifier: License :: OSI Approved :: Apache Software License
Classifier: Operating System :: OS Independent
Classifier: Programming Language :: Python
Classifier: Programming Language :: Python :: 3
Classifier: Programming Language :: Python :: 3.9
License-File: LICENSE
Requires-Dist: scipy
Requires-Dist: py2neo
Requires-Dist: numpy
Requires-Dist: pandas
Requires-Dist: networkx
Requires-Dist: tqdm
Requires-Dist: scikit-learn
Requires-Dist: tackle-dgi
Requires-Dist: rich
Provides-Extra: dev
Requires-Dist: nose (==1.3.7) ; extra == 'dev'
Requires-Dist: pinocchio (==0.4.3) ; extra == 'dev'
Requires-Dist: coverage (==6.3.2) ; extra == 'dev'
Requires-Dist: pylint (==2.13) ; extra == 'dev'
Requires-Dist: ipdb ; extra == 'dev'
